pythology/__init__.py
pythology/functions.py
pythology-1.0.8.dist-info/METADATA
pythology-1.0.8.dist-info/WHEEL
pythology-1.0.8.dist-info/top_level.txt
pythology-1.0.8.dist-info/RECORD
