Metadata-Version: 2.1
Name: pythology
Version: 1.0.8
Summary: Library dedicated to epidemiological compartmental modeling
Home-page: UNKNOWN
Author: Wallace Correa de Moura Filho
Author-email: wallacecmf@poli.ufrj.br
License: MIT
Platform: UNKNOWN
Requires-Python: >=3.8
Requires-Dist: numpy
Requires-Dist: scipy
